gpt_readme/__init__.py
gpt_readme/__main__.py
gpt_readme/constants.py
gpt_readme/dir_summary.py
gpt_readme/file_summary.py
gpt_readme/llm.py
gpt_readme/main.py
gpt_readme/prompts.py
gpt_readme/utils.py
gpt_readme-0.1.2.dist-info/METADATA
gpt_readme-0.1.2.dist-info/WHEEL
gpt_readme-0.1.2.dist-info/entry_points.txt
gpt_readme-0.1.2.dist-info/top_level.txt
gpt_readme-0.1.2.dist-info/RECORD
