Metadata-Version: 2.1
Name: gpt-readme
Version: 0.1.2
Summary: Use ChatGPT to generate a well-formatted README based on your code
Home-page: https://github.com/gusye1234/gpt-readme
Author: JianbaiYe
Classifier: Programming Language :: Python :: 3
Classifier: License :: OSI Approved :: MIT License
Classifier: Operating System :: OS Independent
Requires-Python: >=3.8
Requires-Dist: openai
Requires-Dist: rich
Requires-Dist: gitignore-parser
